{"is_source_file": false, "format": null, "description": null, "external_files": [], "external_methods": [], "published": [], "classes": [], "methods": [], "calls": [], "search-terms": ["config.xml", "Tizen", "widget", "application", "features", "privileges", "metadata"], "state": 2, "file_id": 31, "knowledge_revision": 152, "git_revision": "", "hash": "2f7a6522f82e6538a44c3ca3e779d5dd", "format-version": 4, "code-base-name": "smart-tv-app", "filename": "tizen-tv-app/config.xml", "revision_history": [{"152": ""}]}